setup.py
acra/__init__.py
acra/admin.py
acra/decorators.py
acra/models.py
acra/urls.py
acra/views.py
acra/migrations/0001_initial.py
acra/migrations/__init__.py
django_acra_backend.egg-info/PKG-INFO
django_acra_backend.egg-info/SOURCES.txt
django_acra_backend.egg-info/dependency_links.txt
django_acra_backend.egg-info/not-zip-safe
django_acra_backend.egg-info/requires.txt
django_acra_backend.egg-info/top_level.txt