Metadata-Version: 1.1
Name: django-acra-backend
Version: 0.2.2
Summary: Django model and admin page for ACRA
Home-page: http://github.com/ionata/django-acra-backend
Author: Ionata Digital
Author-email: webmaster@ionata.com.au
License: BSD
Platform: UNKNOWN
Classifier: Development Status :: 4 - Beta
Classifier: Environment :: Web Environment
Classifier: Framework :: Django
Classifier: Intended Audience :: Developers
Classifier: License :: OSI Approved :: BSD License
Classifier: Operating System :: OS Independent
Classifier: Programming Language :: Python
Classifier: Programming Language :: Python :: 2
Classifier: Programming Language :: Python :: 2.7
Classifier: Programming Language :: Python :: 3
Classifier: Programming Language :: Python :: 3.5
